iris/__init__.py
iris/__main__.py
iris/api.py
iris/app_stats.py
iris/cache.py
iris/client.py
iris/config.py
iris/constants.py
iris/custom_import.py
iris/custom_incident_handler.py
iris/db.py
iris/doc_helper.py
iris/gmail.py
iris/sphinx_extension.py
iris/utils.py
iris/applications/__init__.py
iris/applications/dummy_app.py
iris/bin/__init__.py
iris/bin/app_stats.py
iris/bin/iris_ctl.py
iris/bin/owasync.py
iris/bin/retention.py
iris/bin/run_server.py
iris/bin/sender.py
iris/bin/sync_targets.py
iris/bin/ui_build_assets.py
iris/coordinator/__init__.py
iris/coordinator/kazoo.py
iris/coordinator/noncluster.py
iris/metrics/__init__.py
iris/metrics/dummy.py
iris/metrics/influx.py
iris/metrics/prometheus.py
iris/plugins/__init__.py
iris/plugins/core.py
iris/push/__init__.py
iris/push/fcm.py
iris/role_lookup/__init__.py
iris/role_lookup/dummy.py
iris/role_lookup/mailing_list.py
iris/role_lookup/oncall.py
iris/role_lookup/user.py
iris/sender/__init__.py
iris/sender/auditlog.py
iris/sender/cache.py
iris/sender/message.py
iris/sender/metric.py
iris/sender/oneclick.py
iris/sender/quota.py
iris/sender/rpc.py
iris/sender/shared.py
iris/ui/__init__.py
iris/ui/auth/__init__.py
iris/ui/auth/ldap.py
iris/ui/auth/noauth.py
iris/ui/static/css/bootstrap-datetimepicker.css
iris/ui/static/css/bootstrap-theme.css
iris/ui/static/css/bootstrap-theme.min.css
iris/ui/static/css/bootstrap.css
iris/ui/static/css/bootstrap.min.css
iris/ui/static/css/hopscotch.min.css
iris/ui/static/css/iris.css
iris/ui/static/css/jquery.dataTables.min.css
iris/ui/static/fonts/glyphicons-halflings-regular.eot
iris/ui/static/fonts/glyphicons-halflings-regular.svg
iris/ui/static/fonts/glyphicons-halflings-regular.ttf
iris/ui/static/fonts/glyphicons-halflings-regular.woff
iris/ui/static/fonts/glyphicons-halflings-regular.woff2
iris/ui/static/images/chevron-down.png
iris/ui/static/images/iris-1100.png
iris/ui/static/images/iris-small.png
iris/ui/static/images/iris.png
iris/ui/static/images/iris.svg
irisapi-1.0.37.dist-info/AUTHORS.md
irisapi-1.0.37.dist-info/LICENSE
irisapi-1.0.37.dist-info/METADATA
irisapi-1.0.37.dist-info/NOTICE
irisapi-1.0.37.dist-info/WHEEL
irisapi-1.0.37.dist-info/entry_points.txt
irisapi-1.0.37.dist-info/top_level.txt
irisapi-1.0.37.dist-info/RECORD
