Metadata-Version: 2.1
Name: irisapi
Version: 1.0.37
Summary: Iris is a highly configurable and flexible service for paging and messaging.
Home-page: https://github.com/linkedin/iris
License: UNKNOWN
Platform: UNKNOWN
Classifier: Development Status :: 5 - Production/Stable
Classifier: License :: OSI Approved :: BSD License
Classifier: Natural Language :: English
Classifier: Programming Language :: Python :: 3
License-File: LICENSE
License-File: NOTICE
License-File: AUTHORS.md
Requires-Dist: streql (==3.0.2)
Requires-Dist: dnspython
Requires-Dist: phonenumbers (==7.4.1)
Requires-Dist: twilio (==6.25.0)
Requires-Dist: google-api-python-client (==1.4.2)
Requires-Dist: oauth2client (==1.4.12)
Requires-Dist: slackclient (==0.16)
Requires-Dist: PyYAML
Requires-Dist: greenlet (==0.4.16)
Requires-Dist: gevent (==1.5.0)
Requires-Dist: falcon (==1.4.1)
Requires-Dist: falcon-cors
Requires-Dist: ujson (==1.35)
Requires-Dist: requests
Requires-Dist: PyMySQL (==0.9.3)
Requires-Dist: SQLAlchemy (==1.3.0)
Requires-Dist: Jinja2
Requires-Dist: Markdown
Requires-Dist: click
Requires-Dist: msgpack (==1.0.0)
Requires-Dist: cssmin
Requires-Dist: beaker
Requires-Dist: cryptography (==2.3)
Requires-Dist: webassets
Requires-Dist: python-ldap (==3.1.0)
Requires-Dist: exchangelib (==2.2.0)
Requires-Dist: setproctitle
Requires-Dist: pyfcm (==1.4.3)
Requires-Dist: oncallclient (==1.0.0)
Requires-Dist: idna (==2.7)
Requires-Dist: pyqrcode (==1.2.1)
Provides-Extra: dev
Requires-Dist: gunicorn ; extra == 'dev'
Requires-Dist: Sphinx (==1.5.6) ; extra == 'dev'
Requires-Dist: sphinxcontrib-httpdomain ; extra == 'dev'
Requires-Dist: sphinx-rtd-theme ; extra == 'dev'
Requires-Dist: mock (==2.0.0) ; extra == 'dev'
Requires-Dist: pytest (==5.2.0) ; extra == 'dev'
Requires-Dist: pytest-mock (==1.5.0) ; extra == 'dev'
Requires-Dist: pytest-cov ; extra == 'dev'
Requires-Dist: flake8 (==3.5.0) ; extra == 'dev'
Requires-Dist: tox ; extra == 'dev'
Requires-Dist: requests-mock (==1.1.0) ; extra == 'dev'
Provides-Extra: influxdb
Requires-Dist: influxdb ; extra == 'influxdb'
Provides-Extra: kazoo
Requires-Dist: kazoo (==2.6.1) ; extra == 'kazoo'
Provides-Extra: prometheus
Requires-Dist: prometheus-client ; extra == 'prometheus'
